hyper/__init__.py
hyper/certs.pem
hyper/cli.py
hyper/compat.py
hyper/contrib.py
hyper/httplib_compat.py
hyper/ssl_compat.py
hyper/tls.py
hyper/common/__init__.py
hyper/common/bufsocket.py
hyper/common/connection.py
hyper/common/decoder.py
hyper/common/exceptions.py
hyper/common/headers.py
hyper/common/util.py
hyper/http11/__init__.py
hyper/http11/connection.py
hyper/http11/parser.py
hyper/http11/response.py
hyper/http20/__init__.py
hyper/http20/connection.py
hyper/http20/errors.py
hyper/http20/exceptions.py
hyper/http20/response.py
hyper/http20/stream.py
hyper/http20/util.py
hyper/http20/window.py
hyper/packages/__init__.py
hyper/packages/rfc3986/LICENSE
hyper/packages/rfc3986/__init__.py
hyper/packages/rfc3986/api.py
hyper/packages/rfc3986/compat.py
hyper/packages/rfc3986/exceptions.py
hyper/packages/rfc3986/misc.py
hyper/packages/rfc3986/normalizers.py
hyper/packages/rfc3986/parseresult.py
hyper/packages/rfc3986/uri.py
hyper_up-0.8.0.dist-info/LICENSE
hyper_up-0.8.0.dist-info/METADATA
hyper_up-0.8.0.dist-info/NOTICES
hyper_up-0.8.0.dist-info/WHEEL
hyper_up-0.8.0.dist-info/entry_points.txt
hyper_up-0.8.0.dist-info/top_level.txt
hyper_up-0.8.0.dist-info/RECORD
