Metadata-Version: 2.1
Name: hyper-up
Version: 0.8.0
Summary: HTTP/2 Client for Python
Home-page: https://github.com/vasanski/hyper
Author: Eduard Vasanski
Author-email: eduard.vasanski@gmail.com
License: MIT License
Platform: UNKNOWN
Classifier: Development Status :: 3 - Alpha
Classifier: Intended Audience :: Developers
Classifier: License :: OSI Approved :: MIT License
Classifier: Programming Language :: Python
Classifier: Programming Language :: Python :: 2
Classifier: Programming Language :: Python :: 2.7
Classifier: Programming Language :: Python :: 3
Classifier: Programming Language :: Python :: 3.4
Classifier: Programming Language :: Python :: 3.5
Classifier: Programming Language :: Python :: Implementation :: CPython
License-File: LICENSE
License-File: NOTICES
Requires-Dist: h2 (>=2.4)
Requires-Dist: hyperframe (>=3.2)
Requires-Dist: cryptography (<1.0) ; platform_python_implementation == "PyPy" and python_full_version < "2.7.9"
Requires-Dist: pyOpenSSL (>=0.15) ; python_full_version < "2.7.9"
Requires-Dist: service-identity (>=14.0.0) ; python_full_version < "2.7.9"
Provides-Extra: fast
Requires-Dist: pycohttpparser ; extra == 'fast'
